widgetastic_patternfly5/__init__.py
widgetastic_patternfly5/ouia.py
widgetastic_patternfly5/charts/__init__.py
widgetastic_patternfly5/charts/alerts_timeline_chart.py
widgetastic_patternfly5/charts/boxplot_chart.py
widgetastic_patternfly5/charts/bullet_chart.py
widgetastic_patternfly5/charts/donut_chart.py
widgetastic_patternfly5/charts/legend.py
widgetastic_patternfly5/charts/line_chart.py
widgetastic_patternfly5/charts/pie_chart.py
widgetastic_patternfly5/components/__init__.py
widgetastic_patternfly5/components/alert.py
widgetastic_patternfly5/components/breadcrumb.py
widgetastic_patternfly5/components/button.py
widgetastic_patternfly5/components/card.py
widgetastic_patternfly5/components/chip.py
widgetastic_patternfly5/components/clipboard_copy.py
widgetastic_patternfly5/components/description_list.py
widgetastic_patternfly5/components/drawer.py
widgetastic_patternfly5/components/dual_list_selector.py
widgetastic_patternfly5/components/expandable_section.py
widgetastic_patternfly5/components/modal.py
widgetastic_patternfly5/components/navigation.py
widgetastic_patternfly5/components/pagination.py
widgetastic_patternfly5/components/popover.py
widgetastic_patternfly5/components/progress.py
widgetastic_patternfly5/components/slider.py
widgetastic_patternfly5/components/switch.py
widgetastic_patternfly5/components/table.py
widgetastic_patternfly5/components/tabs.py
widgetastic_patternfly5/components/title.py
widgetastic_patternfly5/components/date_and_time/calendar_month.py
widgetastic_patternfly5/components/forms/__init__.py
widgetastic_patternfly5/components/forms/form_select.py
widgetastic_patternfly5/components/forms/radio.py
widgetastic_patternfly5/components/menus/__init__.py
widgetastic_patternfly5/components/menus/context_selector.py
widgetastic_patternfly5/components/menus/dropdown.py
widgetastic_patternfly5/components/menus/menu.py
widgetastic_patternfly5/components/menus/menu_toggle.py
widgetastic_patternfly5/components/menus/options_menu.py
widgetastic.patternfly5-25.7.30.0.dist-info/METADATA
widgetastic.patternfly5-25.7.30.0.dist-info/WHEEL
widgetastic.patternfly5-25.7.30.0.dist-info/licenses/LICENSE
widgetastic.patternfly5-25.7.30.0.dist-info/RECORD
