Metadata-Version: 2.4
Name: widgetastic.patternfly5
Version: 25.7.30.0
Summary: Patternfly5 widget library for Widgetastic.
Project-URL: repository, https://github.com/RedHatQE/widgetastic.patternfly5
Maintainer-email: Nikhil Dhandre <ndhandre@redhat.com>, Egor Shamardin <eshamard@redhat.com>, Mike Shriver <mshriver@redhat.com>
License: Copyright 2023 Red Hat, Inc. and/or its affiliates
License-File: LICENSE
Keywords: patternfly,patternfly5,widgetastic
Classifier: Programming Language :: Python
Classifier: Programming Language :: Python :: 3
Classifier: Programming Language :: Python :: 3.11
Classifier: Programming Language :: Python :: 3.12
Classifier: Programming Language :: Python :: 3.13
Classifier: Topic :: Software Development :: Libraries :: Python Modules
Classifier: Topic :: Software Development :: Quality Assurance
Classifier: Topic :: Software Development :: Testing
Requires-Python: >=3.11
Requires-Dist: widgetastic-core>=1.0.6
Provides-Extra: dev
Requires-Dist: codecov; extra == 'dev'
Requires-Dist: pre-commit; extra == 'dev'
Requires-Dist: pytest; extra == 'dev'
Requires-Dist: pytest-cov; extra == 'dev'
Requires-Dist: pytest-rerunfailures; extra == 'dev'
Requires-Dist: pytest-xdist; extra == 'dev'
Provides-Extra: doc
Requires-Dist: sphinx; extra == 'doc'
